Workbook

Sheet Unit Prices
A1: OPAIJA Production - Unit Prices
A2: All inputs in BLUE - change to model alternative scenarios
A3: Pricing as of mid-2025 - VERIFY before scaling
A5: Item | B5: Unit | C5: Price ($) | D5: Notes
A6: Claude Sonnet 4.5 - input | B6: per 1M tokens | C6: 3 | D6: Anthropic API; primary script brain
A7: Claude Sonnet 4.5 - output | B7: per 1M tokens | C7: 15 | D7: Anthropic API
A8: Claude Haiku 3.5 - input | B8: per 1M tokens | C8: 0.8 | D8: Cheap tier (good for QA)
A9: Claude Haiku 3.5 - output | B9: per 1M tokens | C9: 4 | D9: Cheap tier
A10: Claude Opus 4.1 - input | B10: per 1M tokens | C10: 15 | D10: Premium tier
A11: Claude Opus 4.1 - output | B11: per 1M tokens | C11: 75 | D11: Premium tier
A12: OpenAI GPT-4o - input | B12: per 1M tokens | C12: 2.5 | D12: Alternative brain
A13: OpenAI GPT-4o - output | B13: per 1M tokens | C13: 10 | D13: Alternative brain
A14: OpenAI GPT-4o-mini - input | B14: per 1M tokens | C14: 0.15 | D14: Cheap alt
A15: OpenAI GPT-4o-mini - output | B15: per 1M tokens | C15: 0.6 | D15: Cheap alt
A16: ElevenLabs Multilingual v2 | B16: per 1K chars | C16: 0.3 | D16: Premium voice (Web-Teller)
A17: ElevenLabs Flash v2.5 | B17: per 1K chars | C17: 0.15 | D17: Faster/cheaper, lower quality
... A25: Cloudflare R2 storage | B25: per GB-month | C25: 0.015 | D25: Negligible at this scale

Sheet Format Specs
A1: Format Specifications - Inputs per Deliverable
A2: All inputs in BLUE - adjust runtime, rework factor, image count, etc.
A4: Spec | B4: Vertical 75s | C4: 30-min Episode | D4: 60-min Movie
A5: Runtime (seconds) | B5: 75 | C5: 1800 | D5: 3600
A6: Narration words (~140 wpm) | B6: 170 | C6: 4200 | D6: 8400
A7: Narration chars (=words x 5.5) | B7: =B6*5.5 -> 935 | C7: =C6*5.5 -> 23100 | D7: =D6*5.5 -> 46200
A8: Script Claude input tokens | B8: 1500 | C8: 5000 | D8: 10000
A9: Script Claude output tokens | B9: 500 | C9: 3000 | D9: 6000
A10: Canon QA Claude input tokens | B10: 1000 | C10: 3000 | D10: 5000
A11: Canon QA Claude output tokens | B11: 200 | C11: 800 | D11: 1500
A12: Video clip length (sec) | B12: 5 | C12: 5 | D12: 5
A13: Rework factor (1.5 = 50% extra) | B13: 1.5 | C13: 1.5 | D13: 1.5
A14: Raw clips needed (formula) | B14: =B5/B12*B13 -> 22.5 | C14: =C5/C12*C13 -> 540 | D14: =D5/D12*D13 -> 1080
A15: Character ref images | B15: 5 | C15: 20 | D15: 40
A16: Music minutes (formula) | B16: =B5/60 -> 1.25 | C16: =C5/60 -> 30 | D16: =D5/60 -> 60
A17: Storage per deliverable (GB) | B17: 0.05 | C17: 0.5 | D17: 1

Sheet Cost Model
A1: Per-Asset Cost Breakdown
A2: All cells are formulas pulling from 'Unit Prices' and 'Format Specs' tabs
A4: Cost Line | B4: Vertical 75s | C4: 30-min Episode | D4: 60-min Movie
A5: Script generation (Claude Sonnet 4.5) | B5: =('Format Specs'!B8/1000000)*'Unit Prices'!$C$6+('Format Specs'!B9/1000000)*'Unit Prices'!$C$7 -> 0.012 | C5: =('Format Specs'!C8/1000000)*'Unit Prices'!$C$6+('Format Specs'!C9/1000000)*'Unit Prices'!$C$7 -> 0.06 | D5: =('Format Specs'!D8/1000000)*'Unit Prices'!$C$6+('Format Specs'!D9/1000000)*'Unit Prices'!$C$7 -> 0.12
A6: Canon QA (Claude Sonnet 4.5) | B6: =('Format Specs'!B10/1000000)*'Unit Prices'!$C$6+('Format Specs'!B11/1000000)*'Unit Prices'!$C$7 -> 0.006 | C6: =('Format Specs'!C10/1000000)*'Unit Prices'!$C$6+('Format Specs'!C11/1000000)*'Unit Prices'!$C$7 -> 0.021 | D6: =('Format Specs'!D10/1000000)*'Unit Prices'!$C$6+('Format Specs'!D11/1000000)*'Unit Prices'!$C$7 -> 0.0375
A7: Narration (ElevenLabs Multilingual v2) | B7: =('Format Specs'!B7/1000)*'Unit Prices'!$C$16 -> 0.2805 | C7: =('Format Specs'!C7/1000)*'Unit Prices'!$C$16 -> 6.93 | D7: =('Format Specs'!D7/1000)*'Unit Prices'!$C$16 -> 13.86
A8: Video - Seedance 2.0 Pro (1080p) | B8: ='Format Specs'!B14*'Unit Prices'!$C$18 -> 13.95 | C8: ='Format Specs'!C14*'Unit Prices'!$C$18 -> 334.8 | D8: ='Format Specs'!D14*'Unit Prices'!$C$18 -> 669.6
A9: Video - Seedance 2.0 Lite (720p) [alt] | B9: ='Format Specs'!B14*'Unit Prices'!$C$19 -> 4.05 | C9: ='Format Specs'!C14*'Unit Prices'!$C$19 -> 97.2 | D9: ='Format Specs'!D14*'Unit Prices'!$C$19 -> 194.4
A10: Character ref images (Flux Pro) | B10: ='Format Specs'!B15*'Unit Prices'!$C$22 -> 0.25 | C10: ='Format Specs'!C15*'Unit Prices'!$C$22 -> 1 | D10: ='Format Specs'!D15*'Unit Prices'!$C$22 -> 2
A11: Music (Suno, amortized) | B11: ='Format Specs'!B16*'Unit Prices'!$C$24 -> 0.125 | C11: ='Format Specs'!C16*'Unit Prices'!$C$24 -> 3 | D11: ='Format Specs'!D16*'Unit Prices'!$C$24 -> 6
A12: Storage (R2, first month) | B12: ='Format Specs'!B17*'Unit Prices'!$C$25 -> 0.00075 | C12: ='Format Specs'!C17*'Unit Prices'!$C$25 -> 0.0075 | D12: ='Format Specs'!D17*'Unit Prices'!$C$25 -> 0.015
A14: TOTAL - Pro tier (1080p) | B14: =SUM(B5:B8)+SUM(B10:B12) -> 14.62425 | C14: =SUM(C5:C8)+SUM(C10:C12) -> 345.8185 | D14: =SUM(D5:D8)+SUM(D10:D12) -> 691.6325
A15: TOTAL - Lite tier (720p) | B15: =SUM(B5:B7)+B9+SUM(B10:B12) -> 4.72425 | C15: =SUM(C5:C7)+C9+SUM(C10:C12) -> 108.2185 | D15: =SUM(D5:D7)+D9+SUM(D10:D12) -> 216.4325
A17: Cost per second of finished output | B17: =B14/'Format Specs'!B5 -> 0.19499 | C17: =C14/'Format Specs'!C5 -> 0.19212139 | D17: =D14/'Format Specs'!D5 -> 0.19212014
A18: Cost per minute (Pro) | B18: =B14/('Format Specs'!B5/60) -> 11.6994 | C18: =C14/('Format Specs'!C5/60) -> 11.527283 | D18: =D14/('Format Specs'!D5/60) -> 11.527208

Sheet Monthly Plans
A1: Monthly Production Cost Scenarios
A2: Adjust counts in BLUE to model your cadence
A4: Scenario | B4: Verticals / mo | C4: 30-min eps / mo | D4: 60-min movies / mo | E4: Monthly Cost (Pro) | F4: Monthly Cost (Lite)
A5: Launch - daily verticals (30/mo) | B5: 30 | C5: 0 | D5: 0 | E5: =B5*'Cost Model'!$B$14+C5*'Cost Model'!$C$14+D5*'Cost Model'!$D$14 -> 438.7275 | F5: =B5*'Cost Model'!$B$15+C5*'Cost Model'!$C$15+D5*'Cost Model'!$D$15 -> 141.7275
A6: Light - weekly verticals | B6: 4 | C6: 0 | D6: 0 | E6: =B6*'Cost Model'!$B$14+C6*'Cost Model'!$C$14+D6*'Cost Model'!$D$14 -> 58.497 | F6: =B6*'Cost Model'!$B$15+C6*'Cost Model'!$C$15+D6*'Cost Model'!$D$15 -> 18.897
A7: Series push - 2x 30-min eps | B7: 0 | C7: 2 | D7: 0 | E7: =B7*'Cost Model'!$B$14+C7*'Cost Model'!$C$14+D7*'Cost Model'!$D$14 -> 691.637 | F7: =B7*'Cost Model'!$B$15+C7*'Cost Model'!$C$15+D7*'Cost Model'!$D$15 -> 216.437
A8: Feature push - 1 movie | B8: 0 | C8: 0 | D8: 1 | E8: =B8*'Cost Model'!$B$14+C8*'Cost Model'!$C$14+D8*'Cost Model'!$D$14 -> 691.6325 | F8: =B8*'Cost Model'!$B$15+C8*'Cost Model'!$C$15+D8*'Cost Model'!$D$15 -> 216.4325
A9: Hybrid - 30 shorts + 2 eps + 1 movie | B9: 30 | C9: 2 | D9: 1 | E9: =B9*'Cost Model'!$B$14+C9*'Cost Model'!$C$14+D9*'Cost Model'!$D$14 -> 1821.997 | F9: =B9*'Cost Model'!$B$15+C9*'Cost Model'!$C$15+D9*'Cost Model'!$D$15 -> 574.597
A10: Hyper - 30 shorts + 4 eps | B10: 30 | C10: 4 | D10: 0 | E10: =B10*'Cost Model'!$B$14+C10*'Cost Model'!$C$14+D10*'Cost Model'!$D$14 -> 1822.0015 | F10: =B10*'Cost Model'!$B$15+C10*'Cost Model'!$C$15+D10*'Cost Model'!$D$15 -> 574.6015
A11: Custom (edit counts in blue) | B11: 0 | C11: 0 | D11: 0 | E11: =B11*'Cost Model'!$B$14+C11*'Cost Model'!$C$14+D11*'Cost Model'!$D$14 -> 0 | F11: =B11*'Cost Model'!$B$15+C11*'Cost Model'!$C$15+D11*'Cost Model'!$D$15 -> 0

Sheet Notes
A1: Cost Model - Notes & Caveats
A3: PRICING ASSUMPTIONS (verify at launch time):
A4: - Claude/OpenAI rates as of mid-2025. Anthropic and OpenAI both lowered prices in 2024-2025; check current rates.
A5: - ElevenLabs: Pay-as-you-go rate. Pro subscription ($99/mo for 500K chars + overage at $0.18/1K) is cheaper above ~330K chars/month.
A6: - Seedance 2.0 via fal.ai: $0.62/5s at 1080p (Pro) or $0.18/5s at 720p (Lite). Confirm exact tier in fal.ai dashboard before scaling.
A7: - Pricing assumes English narration; multilingual / pro voice cloning may cost more.
A9: REWORK FACTOR (default 1.5x):
A10: - Real AI video workflows discard 30-50% of generated clips for quality/consistency.
A11: - Adjust in 'Format Specs' sheet (row 13).
A12: - Conservative shops use 2-3x for narrative continuity work.
A14: WHAT IS NOT INCLUDED IN THESE NUMBERS:
A15: - Your time / editor time (largest hidden cost).
... A45: - Movies are cheapest per minute (overhead amortized).
